balancerdata/DataBalancer.py
balancerdata/__init__.py
balancerdata-0.0.1.dist-info/METADATA
balancerdata-0.0.1.dist-info/WHEEL
balancerdata-0.0.1.dist-info/licenses/LICENSE
balancerdata-0.0.1.dist-info/RECORD
