Metadata-Version: 2.1
Name: balancerdata
Version: 0.0.1
Summary: Creacion de la libreria para balancear datos
Project-URL: Homepage, https://github.com/ikergabirondo/Balance_library
Project-URL: Bug Tracker, https://github.com/ikergabirondo/Balance_library/issues
Author-email: ikerg <iker.gabirondo@alumni.mondragon.edu>
License: MIT License
License-File: LICENSE
Classifier: License :: OSI Approved :: MIT License
Classifier: Operating System :: OS Independent
Classifier: Programming Language :: Python :: 3
Requires-Python: >=3.9
